verjava/__init__.py
verjava/commit.py
verjava/definitions.py
verjava/main.py
verjava/meta.py
verjava/util.py
verjava-0.0.3.dist-info/licenses/LICENSE
verjava-0.0.3.dist-info/METADATA
verjava-0.0.3.dist-info/WHEEL
verjava-0.0.3.dist-info/top_level.txt
verjava-0.0.3.dist-info/RECORD
