Metadata-Version: 2.4
Name: verjava
Version: 0.0.3
Summary: Replication of VERJava
Author-email: SunBK201 <sunbk201gm@gmail.com>
Project-URL: Homepage, https://github.com/SunBK201/VERJava
Project-URL: Issues, https://github.com/SunBK201/VERJava/issues
Classifier: Programming Language :: Python :: 3
Classifier: License :: OSI Approved :: MIT License
Classifier: Operating System :: OS Independent
Classifier: Programming Language :: Python
Requires-Python: >=3.10
License-File: LICENSE
Requires-Dist: scubatrace==0.7.0
Requires-Dist: GitPython>=3.1.43
Dynamic: license-file
